poseidon_core/__init__.py
poseidon_core/__main__.py
poseidon_core/constants.py
poseidon_core/controllers/__init__.py
poseidon_core/controllers/faucet/__init__.py
poseidon_core/controllers/faucet/config.py
poseidon_core/controllers/faucet/faucet.py
poseidon_core/controllers/sdnconnect.py
poseidon_core/controllers/sdnevents.py
poseidon_core/helpers/__init__.py
poseidon_core/helpers/actions.py
poseidon_core/helpers/collector.py
poseidon_core/helpers/config.py
poseidon_core/helpers/endpoint.py
poseidon_core/helpers/exception_decor.py
poseidon_core/helpers/log.py
poseidon_core/helpers/metadata.py
poseidon_core/helpers/prometheus.py
poseidon_core/helpers/rabbit.py
poseidon_core/main.py
poseidon_core/metadata/nmap-mac-prefixes.txt
poseidon_core/operations/__init__.py
poseidon_core/operations/monitor.py
poseidon_core/operations/primitives/__init__.py
poseidon_core/operations/primitives/acl.py
poseidon_core/operations/primitives/coprocess.py
poseidon_core/operations/primitives/meter.py
poseidon_core/operations/primitives/mirror.py
poseidon_core/operations/volos/__init__.py
poseidon_core/operations/volos/acls.py
poseidon_core/operations/volos/volos.py
poseidon_core-0.18.2.dist-info/entry_points.txt
poseidon_core-0.18.2.dist-info/WHEEL
poseidon_core-0.18.2.dist-info/METADATA
poseidon_core-0.18.2.dist-info/RECORD
