Metadata-Version: 2.1
Name: poseidon-core
Version: 0.18.2
Summary: Poseidon core package, an application that leverages software defined networks (SDN) to acquire and then feed network traffic to a number of analytic tools.
License: Apache-2.0
Author: cglewis
Author-email: clewis@iqt.org
Requires-Python: >=3.8,<3.11
Classifier: License :: OSI Approved :: Apache Software License
Classifier: Programming Language :: Python :: 3
Classifier: Programming Language :: Python :: 3.8
Classifier: Programming Language :: Python :: 3.9
Classifier: Programming Language :: Python :: 3.10
Requires-Dist: faucetconfrpc (==0.22.40)
Requires-Dist: httpx (==0.23.0)
Requires-Dist: netaddr (==0.8.0)
Requires-Dist: pika (==1.3.0)
Requires-Dist: prometheus_client (==0.14.1)
Requires-Dist: pyyaml (==6.0)
Requires-Dist: schedule (==1.1.0)
Requires-Dist: transitions (==0.9.0)
Project-URL: homepage, https://github.com/IQTLabs/poseidon
